apiconsumer/__init__.py
apiconsumer/apiconsumer.py
apiconsumer/core.py
apiconsumer/exceptions.py
apiconsumer/tests.py
apiconsumer-1.0.0b3.dist-info/DESCRIPTION.rst
apiconsumer-1.0.0b3.dist-info/METADATA
apiconsumer-1.0.0b3.dist-info/metadata.json
apiconsumer-1.0.0b3.dist-info/RECORD
apiconsumer-1.0.0b3.dist-info/top_level.txt
apiconsumer-1.0.0b3.dist-info/WHEEL
