Metadata-Version: 2.0
Name: apiconsumer
Version: 1.0.0b3
Summary: Lightweight requests wrapper for REST API calls
Home-page: https://github.com/saberr/apiconsumer
Author: Marko Stanojkovic
Author-email: marko@saberr.com
License: BSD 3-Clause
Platform: UNKNOWN
Classifier: Development Status :: 4 - Beta
Classifier: Intended Audience :: Developers
Classifier: Topic :: Software Development :: Build Tools
Classifier: License :: OSI Approved :: BSD License
Classifier: Programming Language :: Python :: 2
Classifier: Programming Language :: Python :: 2.7
Classifier: Programming Language :: Python :: 3
Classifier: Programming Language :: Python :: 3.4
Classifier: Programming Language :: Python :: 3.5
Classifier: Programming Language :: Python :: 3.6
Requires-Dist: requests (>=2.18.4)
